termcolor/__init__.py
termcolor/py.typed
termcolor/termcolor.py
termcolor-2.0.0.dist-info/METADATA
termcolor-2.0.0.dist-info/WHEEL
termcolor-2.0.0.dist-info/licenses/COPYING.txt
termcolor-2.0.0.dist-info/RECORD
