Metadata-Version: 2.1
Name: termcolor
Version: 2.0.0
Summary: ANSI color formatting for output in terminal
Project-URL: Changelog, https://github.com/termcolor/termcolor/releases
Project-URL: Homepage, https://github.com/termcolor/termcolor
Project-URL: Source, https://github.com/hugovk/termcolor
Author-email: Konstantin Lepa <konstantin.lepa@gmail.com>
Maintainer: Hugo van Kemenade
License: MIT
License-File: COPYING.txt
Keywords: ANSI,ANSI color,ANSI colour,color,colour,formatting,termcolor,terminal
Classifier: Development Status :: 5 - Production/Stable
Classifier: Environment :: Console
Classifier: Intended Audience :: Developers
Classifier: License :: OSI Approved :: MIT License
Classifier: Operating System :: OS Independent
Classifier: Programming Language :: Python
Classifier: Programming Language :: Python :: 3
Classifier: Programming Language :: Python :: 3 :: Only
Classifier: Programming Language :: Python :: 3.7
Classifier: Programming Language :: Python :: 3.8
Classifier: Programming Language :: Python :: 3.9
Classifier: Programming Language :: Python :: 3.10
Classifier: Programming Language :: Python :: 3.11
Classifier: Programming Language :: Python :: Implementation :: CPython
Classifier: Programming Language :: Python :: Implementation :: PyPy
Classifier: Topic :: Terminals
Requires-Python: >=3.7
Provides-Extra: tests
Requires-Dist: pytest; extra == 'tests'
Requires-Dist: pytest-cov; extra == 'tests'
